chromatopy/__init__.py
chromhandler/__init__.py
chromhandler/enzymeml.py
chromhandler/handler.py
chromhandler/internal_standard.py
chromhandler/model.py
chromhandler/molecule.py
chromhandler/pretty.py
chromhandler/protein.py
chromhandler/utility.py
chromhandler/visualize.py
chromhandler/readers/__init__.py
chromhandler/readers/abstractreader.py
chromhandler/readers/agilent_csv.py
chromhandler/readers/agilent_rdl.py
chromhandler/readers/agilent_txt.py
chromhandler/readers/asm.py
chromhandler/readers/chromeleon.py
chromhandler/readers/generic_csv.py
chromhandler/readers/shimadzu.py
chromhandler/readers/thermo_txt.py
chromhandler/units/__init__.py
chromhandler/units/predefined.py
chromhandler-0.10.7.dist-info/METADATA
chromhandler-0.10.7.dist-info/WHEEL
chromhandler-0.10.7.dist-info/licenses/LICENSE
chromhandler-0.10.7.dist-info/RECORD
