Metadata-Version: 2.4
Name: chromhandler
Version: 0.10.7
Summary: Tool for processing chromatography data
Project-URL: Homepage, https://github.com/haeussma/chromhandler
Author-email: haeussma <83341109+haeussma@users.noreply.github.com>
License: MIT
License-File: LICENSE
Requires-Python: <3.14,>=3.11
Requires-Dist: calipytion<2.0.0,>=1.0.2
Requires-Dist: loguru<1,>=0.7
Requires-Dist: numpy<=2.1.0
Requires-Dist: pydantic<3,>=2
Requires-Dist: pyenzyme<3.0.0,>=2.1.0
Requires-Dist: rich<15,>=13.7
